{
    "agent": {
        "arrival_time_ms": 1591060425870,
        "hangup_time_ms": 1591060512787,
        "metadata": {
            "agent_name": "James"
        },
        "responses": [
            {
                "submit_time_ms": 1591060493871,
                "data": {
                    "company name": "Smart Electric",
                    "money amount": "$61",
                    "task_type": "pay bill",
                    "company address": "520 First St Forrest Ranch CA, 21074"
                }
            }
        ],
        "speaker_id": 46,
        "survey_response": {
            "submit_time_ms": 1591060515914,
            "data": {
                "partner_rating": "10",
                "ease_of_connection": "10"
            }
        }
    },
    "caller": {
        "arrival_time_ms": 1591060408468,
        "hangup_time_ms": 1591060514251,
        "metadata": {
            "first and last name": "Mary Jones"
        },
        "responses": [
            {
                "submit_time_ms": 1591060500423
            }
        ],
        "speaker_id": 57,
        "survey_response": {
            "submit_time_ms": 1591060522535,
            "data": {
                "partner_rating": "10",
                "ease_of_connection": "10"
            }
        }
    },
    "end_time_ms": 1591060512624,
    "sid": "0ec73a168f174a86",
    "start_time_ms": 1591060431793,
    "labels": {
        "caller_mos": 5.0,
        "lhvb_script": 5.0,
        "agent_mos": 5.0
    },
    "session": "Little Harper Valley 3",
    "tasks": [
        {
            "company name": "Smart Electic",
            "money amount": 61,
            "task_type": "pay bill",
            "company address": "520 First Street, Forest Ranch, California, 21074"
        }
    ]
}