{
    "agent": {
        "arrival_time_ms": 1590865163824,
        "hangup_time_ms": 1590865212354,
        "metadata": {
            "agent_name": "John"
        },
        "responses": [
            {
                "submit_time_ms": 1590865196262,
                "data": {
                    "task_type": "reset password",
                    "phone": "9624145882"
                }
            }
        ],
        "speaker_id": 6,
        "survey_response": {
            "submit_time_ms": 1590865210285,
            "data": {}
        }
    },
    "caller": {
        "arrival_time_ms": 1590865156193,
        "hangup_time_ms": 1590865217671,
        "metadata": {
            "first and last name": "Jennifer Brown"
        },
        "responses": [
            {
                "submit_time_ms": 1590865200788
            }
        ],
        "speaker_id": 47,
        "survey_response": {
            "submit_time_ms": 1590865213476,
            "data": {
                "partner_rating": "10",
                "ease_of_connection": "10"
            }
        }
    },
    "end_time_ms": 1590865212200,
    "sid": "141a91d6758747b7",
    "start_time_ms": 1590865169753,
    "labels": {
        "caller_mos": 4.0,
        "lhvb_script": 5.0,
        "agent_mos": 4.0
    },
    "session": "Little Harper Valley 2",
    "tasks": [
        {
            "password dest": "phone",
            "task_type": "reset password",
            "phone": "962-414-5882"
        }
    ]
}