{
    "agent": {
        "arrival_time_ms": 1584314451573,
        "hangup_time_ms": 1584314534407,
        "metadata": {
            "agent_name": "Michael"
        },
        "responses": [
            {
                "submit_time_ms": 1584314515327,
                "data": {
                    "home address": "037 first st forest ranch ca 32714",
                    "task_type": "order checks"
                }
            },
            {
                "submit_time_ms": 1584314541690,
                "data": {
                    "home address": "037 first st forest ranch ca 32714",
                    "task_type": "order checks"
                }
            }
        ],
        "speaker_id": 13,
        "survey_response": {
            "submit_time_ms": 1584314537282,
            "data": {
                "partner_rating": "10",
                "ease_of_connection": "10"
            }
        }
    },
    "caller": {
        "arrival_time_ms": 1584314445795,
        "hangup_time_ms": 1584314539806,
        "metadata": {
            "first and last name": "Linda Miller"
        },
        "responses": [
            {
                "submit_time_ms": 1584314551640
            },
            {
                "submit_time_ms": 1584314554078
            }
        ],
        "speaker_id": 24,
        "survey_response": {
            "submit_time_ms": 1584314532692,
            "data": {}
        }
    },
    "end_time_ms": 1584314534208,
    "sid": "29e0a36fb0c6401e",
    "start_time_ms": 1584314457409,
    "labels": {
        "caller_mos": 4.0,
        "lhvb_script": 5.0,
        "agent_mos": 4.0
    },
    "session": "Little Harper Valley 1",
    "tasks": [
        {
            "home address": "037 First Street, Forest Ranch, California, 32714",
            "task_type": "order checks"
        }
    ]
}