{
    "agent": {
        "arrival_time_ms": 1591060535470,
        "hangup_time_ms": 1591060578261,
        "metadata": {
            "agent_name": "James"
        },
        "responses": [
            {
                "submit_time_ms": 1591060574054,
                "data": {
                    "task_type": "get branch hours"
                }
            }
        ],
        "speaker_id": 47,
        "survey_response": {
            "submit_time_ms": 1591060580282,
            "data": {
                "ease_of_connection": "10",
                "partner_rating": "10"
            }
        }
    },
    "caller": {
        "arrival_time_ms": 1591060535382,
        "hangup_time_ms": 1591060575704,
        "metadata": {
            "first and last name": "Jennifer Wilson"
        },
        "responses": [
            {
                "submit_time_ms": 1591060576484
            }
        ],
        "speaker_id": 35,
        "survey_response": {
            "submit_time_ms": 1591060582468,
            "data": {
                "ease_of_connection": "10",
                "partner_rating": "10"
            }
        }
    },
    "end_time_ms": 1591060575608,
    "sid": "2a4cd03815db469a",
    "start_time_ms": 1591060541398,
    "labels": {
        "lhvb_script": 5.0,
        "agent_mos": 5.0,
        "caller_mos": 5.0
    },
    "session": "Little Harper Valley 3",
    "tasks": [
        {
            "branch hours": "8:30 am to 5:00 pm",
            "task_type": "get branch hours"
        }
    ]
}