{
    "agent": {
        "arrival_time_ms": 1590863348559,
        "hangup_time_ms": 1590863405531,
        "metadata": {
            "agent_name": "Linda"
        },
        "responses": [
            {
                "submit_time_ms": 1590863387464,
                "data": {
                    "transfer destination account": "savings",
                    "transfer amount": "144.00",
                    "transfer source account": "checking",
                    "task_type": "transfer money"
                }
            }
        ],
        "speaker_id": 22,
        "survey_response": {
            "submit_time_ms": 1590863407502,
            "data": {
                "ease_of_connection": "10",
                "partner_rating": "10"
            }
        }
    },
    "caller": {
        "arrival_time_ms": 1590863346225,
        "hangup_time_ms": 1590863405048,
        "metadata": {
            "first and last name": "Robert Smith"
        },
        "responses": [
            {
                "submit_time_ms": 1590863394926
            }
        ],
        "speaker_id": 6,
        "survey_response": {
            "submit_time_ms": 1590863402166,
            "data": {}
        }
    },
    "end_time_ms": 1590863404881,
    "sid": "317c158f88834ca5",
    "start_time_ms": 1590863354477,
    "labels": {
        "lhvb_script": 5.0,
        "caller_mos": 4.0,
        "agent_mos": 5.0
    },
    "session": "Little Harper Valley 2",
    "tasks": [
        {
            "transfer destination account": "savings",
            "transfer amount": 144,
            "transfer source account": "checking",
            "task_type": "transfer money"
        }
    ]
}