{
    "agent": {
        "arrival_time_ms": 1584313947318,
        "hangup_time_ms": 1584314019937,
        "metadata": {
            "agent_name": "Elizabeth"
        },
        "responses": [],
        "speaker_id": 44,
        "survey_response": {
            "submit_time_ms": 1584314017046,
            "data": {
                "partner_rating": "10",
                "ease_of_connection": "10"
            }
        }
    },
    "caller": {
        "arrival_time_ms": 1584313946783,
        "hangup_time_ms": 1584314019114,
        "metadata": {
            "first and last name": "Patricia Rodriguez"
        },
        "responses": [
            {
                "submit_time_ms": 1584313995682
            }
        ],
        "speaker_id": 33,
        "survey_response": {
            "submit_time_ms": 1584314010257,
            "data": {
                "ease_of_connection": "10",
                "partner_rating": "10"
            }
        }
    },
    "end_time_ms": 1584314018951,
    "sid": "3e9a533d616246cb",
    "start_time_ms": 1584313953238,
    "labels": {
        "lhvb_script": 5.0,
        "agent_mos": 5.0,
        "caller_mos": 5.0
    },
    "session": "Little Harper Valley 1",
    "tasks": [
        {
            "branch hours": "8:30 am to 5:00 pm",
            "task_type": "get branch hours"
        }
    ]
}