{
    "agent": {
        "arrival_time_ms": 1590859112814,
        "hangup_time_ms": 1590859195460,
        "metadata": {
            "agent_name": "Elizabeth"
        },
        "responses": [
            {
                "submit_time_ms": 1590859174415,
                "data": {
                    "home address": "834 first street forrest ranch oregon 66793",
                    "task_type": "order checks"
                }
            }
        ],
        "speaker_id": 38,
        "survey_response": {
            "submit_time_ms": 1590859193049,
            "data": {
                "partner_rating": "10",
                "ease_of_connection": "10"
            }
        }
    },
    "caller": {
        "arrival_time_ms": 1590859103262,
        "hangup_time_ms": 1590859191811,
        "metadata": {
            "first and last name": "Patricia Miller"
        },
        "responses": [
            {
                "submit_time_ms": 1590859183921
            }
        ],
        "speaker_id": 0,
        "survey_response": {
            "submit_time_ms": 1590859194210,
            "data": {}
        }
    },
    "end_time_ms": 1590859191691,
    "sid": "57fa3575c7d44c67",
    "start_time_ms": 1590859118768,
    "labels": {
        "caller_mos": 5.0,
        "lhvb_script": 5.0,
        "agent_mos": 5.0
    },
    "session": "Little Harper Valley 2",
    "tasks": [
        {
            "home address": "834 First Street, Forest Ranch, Oregon, 67793",
            "task_type": "order checks"
        }
    ]
}