{
    "agent": {
        "arrival_time_ms": 1590860016421,
        "hangup_time_ms": 1590860068272,
        "metadata": {
            "agent_name": "James"
        },
        "responses": [
            {
                "submit_time_ms": 1590860050509,
                "data": {
                    "task_type": "replace card",
                    "replacement card type": "credit"
                }
            }
        ],
        "speaker_id": 0,
        "survey_response": {
            "submit_time_ms": 1590860073703,
            "data": {}
        }
    },
    "caller": {
        "arrival_time_ms": 1590860012013,
        "hangup_time_ms": 1590860066688,
        "metadata": {
            "first and last name": "Mary Wilson"
        },
        "responses": [
            {
                "submit_time_ms": 1590860056422
            }
        ],
        "speaker_id": 56,
        "survey_response": {
            "submit_time_ms": 1590860067037,
            "data": {
                "ease_of_connection": "10",
                "partner_rating": "10"
            }
        }
    },
    "end_time_ms": 1590860066581,
    "sid": "61281b24a0424127",
    "start_time_ms": 1590860022531,
    "labels": {
        "lhvb_script": 5.0,
        "agent_mos": 5.0,
        "caller_mos": 3.0
    },
    "session": "Little Harper Valley 2",
    "tasks": [
        {
            "task_type": "replace card",
            "replacement card type": "credit"
        }
    ]
}