{
    "agent": {
        "arrival_time_ms": 1584309713898,
        "hangup_time_ms": 1584309805046,
        "metadata": {
            "agent_name": "Elizabeth"
        },
        "responses": [
            {
                "submit_time_ms": 1584309789401,
                "data": {
                    "money amount": "25.00",
                    "task_type": "pay bill",
                    "company name": "Smart Electric",
                    "company address": "563 Main Street Forest Ranch California 79837"
                }
            }
        ],
        "speaker_id": 28,
        "survey_response": {
            "submit_time_ms": 1584309814516,
            "data": {
                "partner_rating": "10",
                "ease_of_connection": "10"
            }
        }
    },
    "caller": {
        "arrival_time_ms": 1584309710683,
        "hangup_time_ms": 1584309806517,
        "metadata": {
            "first and last name": "Linda Davis"
        },
        "responses": [
            {
                "submit_time_ms": 1584309801218
            }
        ],
        "speaker_id": 44,
        "survey_response": {
            "submit_time_ms": 1584309805784,
            "data": {
                "ease_of_connection": "10",
                "partner_rating": "10"
            }
        }
    },
    "end_time_ms": 1584309804908,
    "sid": "a104c589566d46fd",
    "start_time_ms": 1584309719988,
    "labels": {
        "lhvb_script": 4.0,
        "agent_mos": 5.0,
        "caller_mos": 4.0
    },
    "session": "Little Harper Valley 1",
    "tasks": [
        {
            "money amount": 25,
            "task_type": "pay bill",
            "company name": "Smart Electic",
            "company address": "563 Main Street, Forest Ranch, California, 79837"
        }
    ]
}