{
    "agent": {
        "arrival_time_ms": 1590861506274,
        "hangup_time_ms": 1590861561346,
        "metadata": {
            "agent_name": "Linda"
        },
        "responses": [
            {
                "submit_time_ms": 1590861545926,
                "data": {
                    "day": "thursday",
                    "task_type": "schedule appointment",
                    "time": "3:45"
                }
            }
        ],
        "speaker_id": 28,
        "survey_response": {
            "submit_time_ms": 1590861564724,
            "data": {
                "partner_rating": "10",
                "ease_of_connection": "10"
            }
        }
    },
    "caller": {
        "arrival_time_ms": 1590861502219,
        "hangup_time_ms": 1590861563785,
        "metadata": {
            "first and last name": "Linda Rodriguez"
        },
        "responses": [
            {
                "submit_time_ms": 1590861552192
            }
        ],
        "speaker_id": 59,
        "survey_response": {
            "submit_time_ms": 1590861562771,
            "data": {}
        }
    },
    "end_time_ms": 1590861561207,
    "sid": "e46bda445f9a4958",
    "start_time_ms": 1590861512157,
    "labels": {
        "caller_mos": 3.0,
        "lhvb_script": 4.0,
        "agent_mos": 4.0
    },
    "session": "Little Harper Valley 2",
    "tasks": [
        {
            "day": "Thursday",
            "task_type": "schedule appointment",
            "time": "3:45 PM"
        }
    ]
}